LICENSE
MANIFEST.in
README.txt
setup.py
wofrywiser/__init__.py
wofrywiser/version.py
wofrywiser.egg-info/PKG-INFO
wofrywiser.egg-info/SOURCES.txt
wofrywiser.egg-info/dependency_links.txt
wofrywiser.egg-info/not-zip-safe
wofrywiser.egg-info/requires.txt
wofrywiser.egg-info/top_level.txt
wofrywiser/_test/1_initial_test_renamed.py
wofrywiser/_test/2_append_remove_elements.py
wofrywiser/_test/3_test_beamline_dpi_h_fel2.py
wofrywiser/_test/__init__.py
wofrywiser/beamline/__init__.py
wofrywiser/beamline/beamline_elements.py
wofrywiser/propagator/__init__.py
wofrywiser/propagator/propagator1D/__init__.py
wofrywiser/propagator/propagator1D/wise_propagator.py
wofrywiser/propagator/wavefront1D/__init__.py
wofrywiser/propagator/wavefront1D/wise_wavefront.py