Metadata-Version: 2.1
Name: wofrywiser
Version: 0.1.4
Summary: WOFRY (Wave Optics FRamework in pYthon) for Wiser library
Home-page: https://github.com/oasys-elettra-kit/wofrywiser
Author: Luca Rebuffi, Michele Manfredda, Aljosa Hafner
Author-email: michele.manfredda@elettra.eu
Maintainer: Aljosa Hafner
Maintainer-email: aljosa.hafner@ceric-eric.eu
License: GPLv3
Download-URL: https://github.com/oasys-elettra-kit/wofrywiser
Keywords: dictionary,glossary,synchrotron,simulation
Platform: UNKNOWN
Classifier: Development Status :: 4 - Beta
Classifier: Environment :: Console
Classifier: Environment :: Plugins
Classifier: Programming Language :: Python :: 3
Classifier: Intended Audience :: Education
Classifier: Intended Audience :: Science/Research
License-File: LICENSE
